{
  "current": {
    "favicon": "shopify:\/\/shop_images\/favicon-32x32.png",
    "currency_code_enabled": false,
    "checkout_logo_image": "shopify:\/\/shop_images\/AKRAM-logo-02.png",
    "checkout_logo_size": "large",
    "checkout_body_background_color": "#000000",
    "checkout_sidebar_background_color": "#000000",
    "checkout_accent_color": "#a4a4a4",
    "checkout_button_color": "#ffffff",
    "checkout_error_color": "#ef1f1f",
    "sections": {
      "header": {
        "type": "header",
        "settings": {
          "logo_width": 100,
          "logo_position": "middle-left",
          "menu": "main-menu",
          "locked_links": "learn more, archive"
        }
      },
      "footer": {
        "type": "footer",
        "blocks": {
          "1242bf0d-48c0-4b50-a5ed-8dd11906aca3": {
            "type": "link_list",
            "settings": {
              "heading": "Secondary Footer Links",
              "menu": "secondary-footer-menu"
            }
          },
          "a34ccfce-99fe-4f01-9b31-8b235a049c74": {
            "type": "social",
            "settings": {
              "instagram": "https:\/\/www.instagram.com\/akram.nyc\/"
            }
          },
          "footer-0": {
            "type": "link_list",
            "settings": {
              "heading": "Footer Navigation",
              "menu": "footer"
            }
          }
        },
        "block_order": [
          "1242bf0d-48c0-4b50-a5ed-8dd11906aca3",
          "a34ccfce-99fe-4f01-9b31-8b235a049c74",
          "footer-0"
        ],
        "settings": {
          "color_scheme": "background-1",
          "newsletter_enable": false,
          "newsletter_heading": "Sign up to our emails",
          "show_social": false,
          "enable_country_selector": false,
          "enable_language_selector": false,
          "payment_enable": false
        }
      }
    },
    "content_for_index": [

    ]
  }
}
